MANIFEST.in
README.md
setup.py
cssclean/__init__.py
cssclean/logger.py
cssclean/version.py
cssclean.egg-info/PKG-INFO
cssclean.egg-info/SOURCES.txt
cssclean.egg-info/dependency_links.txt
cssclean.egg-info/entry_points.txt
cssclean.egg-info/not-zip-safe
cssclean.egg-info/requires.txt
cssclean.egg-info/top_level.txt
cssclean/client/__init__.py
cssclean/client/clean.py
cssclean/main/__init__.py
cssclean/main/client.py
cssclean/utils/__init__.py
cssclean/utils/docs.py
cssclean/utils/fileio.py
cssclean/utils/inspect.py
cssclean/utils/terminal.py